openfhe/__init__.py
openfhe/build-config.txt
openfhe/openfhe.cpython-312-x86_64-linux-gnu.so
openfhe/lib/libOPENFHEbinfhe.so.1
openfhe/lib/libOPENFHEcore.so.1
openfhe/lib/libOPENFHEpke.so.1
openfhe/lib/libgomp.so
openfhe_wrapper-0.0.8.dist-info/LICENSE
openfhe_wrapper-0.0.8.dist-info/METADATA
openfhe_wrapper-0.0.8.dist-info/WHEEL
openfhe_wrapper-0.0.8.dist-info/top_level.txt
openfhe_wrapper-0.0.8.dist-info/RECORD
